preloader.py
sitemap_preloader-0.1.4.dist-info/METADATA
sitemap_preloader-0.1.4.dist-info/WHEEL
sitemap_preloader-0.1.4.dist-info/top_level.txt
sitemap_preloader-0.1.4.dist-info/RECORD
