Metadata-Version: 2.1
Name: sitemap-preloader
Version: 0.1.4
Summary: This package is used to read a sitemap and fetch all the urls in order to warm the cache of a website
Home-page: https://github.com/andresgz/sitemap-preloader
Author: Andres Gonzalez
Author-email: code@andresgz.com
Classifier: Programming Language :: Python :: 3
Classifier: License :: OSI Approved :: MIT License
Classifier: Operating System :: OS Independent
Requires-Dist: requests
Requires-Dist: beautifulsoup4
Requires-Dist: validators
Requires-Dist: lxml
